kumacub/__init__.py
kumacub/application/services/__init__.py
kumacub/application/services/daemon.py
kumacub/application/services/runner.py
kumacub/config.py
kumacub/data/config.toml
kumacub/data/kumacub.service
kumacub/domain/__init__.py
kumacub/domain/models.py
kumacub/entrypoints/__init__.py
kumacub/entrypoints/cli.py
kumacub/infrastructure/__init__.py
kumacub/infrastructure/executors/__init__.py
kumacub/infrastructure/executors/process_executor.py
kumacub/infrastructure/parsers/__init__.py
kumacub/infrastructure/parsers/nagios.py
kumacub/infrastructure/publishers/__init__.py
kumacub/infrastructure/publishers/stdout.py
kumacub/infrastructure/publishers/uptime_kuma.py
kumacub/logging_config.py
kumacub-0.4.0.dist-info/WHEEL
kumacub-0.4.0.dist-info/entry_points.txt
kumacub-0.4.0.dist-info/METADATA
kumacub-0.4.0.dist-info/RECORD
