Metadata-Version: 2.4
Name: kumacub
Version: 0.4.0
Summary: Run local Nagios-compatible checks; push results to Uptime Kuma
Keywords: nagios,Uptime Kuma
Author: Steve Jibson
Author-email: Steve Jibson <steve@jibson.com>
License-Expression: GPL-3.0-only
Classifier: Development Status :: 2 - Pre-Alpha
Classifier: Programming Language :: Python
Classifier: Programming Language :: Python :: 3
Classifier: Programming Language :: Python :: 3.11
Classifier: Programming Language :: Python :: 3.12
Classifier: Programming Language :: Python :: 3.13
Classifier: Programming Language :: Python :: 3.14
Requires-Dist: apscheduler>=3.11.1
Requires-Dist: httpx>=0.28.1
Requires-Dist: pydantic>=2.12.4
Requires-Dist: pydantic-settings>=2.11.0
Requires-Dist: structlog>=25.5.0
Requires-Python: >=3.11
Project-URL: Documentation, https://github.com/toadstule/kumacub/README.md
Project-URL: Homepage, https://github.com/toadstule/kumacub
Project-URL: Issues, https://github.com/toadstule/kumacub/issues
Project-URL: Repository, https://github.com/toadstule/kumacub.git
